[
    {
        "id": 1,
        "title": "Kiwi Martini",
        "desc": "A cocktail made with Kiwi and Martini",
        "links": "Later",
        "image": "image/kiwi.png"
    },
    {
        "id": 2,
        "title": "Kiwi Martini",
        "desc": "A cocktail made with Kiwi and Martini",
        "links": "Later",
        "image": "image/kiwi.png"
    },
    {
        "id": 3,
        "title": "Kiwi Martini",
        "desc": "A cocktail made with Kiwi and Martini",
        "links": "Later",
        "image": "image/kiwi.png"
    }
]